pixhostuploader/__init__.py
pixhostuploader/pixhost.py
pixhostuploader-1.0.10.dist-info/DESCRIPTION.rst
pixhostuploader-1.0.10.dist-info/METADATA
pixhostuploader-1.0.10.dist-info/metadata.json
pixhostuploader-1.0.10.dist-info/RECORD
pixhostuploader-1.0.10.dist-info/top_level.txt
pixhostuploader-1.0.10.dist-info/WHEEL
