Metadata-Version: 2.0
Name: pixhostuploader
Version: 1.0.10
Summary: Unofficial uploader to pixhost.org image sharing site.
Home-page: https://github.com/martinsik/pixhost-uploader
Author: Martin Sikora
Author-email: UNKNOWN
License: MIT
Platform: UNKNOWN
Classifier: Programming Language :: Python :: 3.2
Classifier: Programming Language :: Python :: 3.3
Classifier: Programming Language :: Python :: 3.4
Classifier: Topic :: Internet
Classifier: Topic :: Multimedia :: Graphics
Classifier: Topic :: Utilities
Requires-Dist: requests
Requires-Dist: lxml
